memofai/__init__.py
memofai/api_client.py
memofai/endpoints.py
memofai/exceptions.py
memofai/http_client.py
memofai/py.typed
memofai/types.py
memofai/version.py
memofai-1.0.0.dist-info/licenses/LICENSE
memofai-1.0.0.dist-info/METADATA
memofai-1.0.0.dist-info/WHEEL
memofai-1.0.0.dist-info/top_level.txt
memofai-1.0.0.dist-info/RECORD
