Metadata-Version: 2.4
Name: memofai
Version: 1.0.0
Summary: Official Python SDK for Memory-of-Agents (MOA) - AI memory infrastructure for intelligent applications
Home-page: https://memof.ai
Author: Memory-of-Agents Team
Author-email: Memory-of-Agents Team <dev@memof.ai>
Maintainer-email: Memory-of-Agents Team <dev@memof.ai>
License: MIT
Project-URL: Homepage, https://memof.ai
Project-URL: Documentation, https://docs.memof.ai
Project-URL: Repository, https://github.com/memof-ai/memofai-python-sdk
Project-URL: Issues, https://github.com/memof-ai/memofai-python-sdk/issues
Project-URL: Changelog, https://github.com/memof-ai/memofai-python-sdk/blob/main/CHANGELOG.md
Keywords: memofai,moa,memory-of-agents,ai-memory,ai,memory,agents,sdk,python,llm,chatbot,agent-memory
Classifier: Development Status :: 4 - Beta
Classifier: Intended Audience :: Developers
Classifier: License :: OSI Approved :: MIT License
Classifier: Operating System :: OS Independent
Classifier: Programming Language :: Python :: 3
Classifier: Programming Language :: Python :: 3.8
Classifier: Programming Language :: Python :: 3.9
Classifier: Programming Language :: Python :: 3.10
Classifier: Programming Language :: Python :: 3.11
Classifier: Programming Language :: Python :: 3.12
Classifier: Topic :: Software Development :: Libraries :: Python Modules
Classifier: Topic :: Scientific/Engineering :: Artificial Intelligence
Classifier: Typing :: Typed
Requires-Python: >=3.8
License-File: LICENSE
Requires-Dist: requests<3.0.0,>=2.28.0
Requires-Dist: urllib3<3.0.0,>=1.26.0
Provides-Extra: dev
Requires-Dist: pytest>=7.0.0; extra == "dev"
Requires-Dist: pytest-cov>=4.0.0; extra == "dev"
Requires-Dist: black>=23.0.0; extra == "dev"
Requires-Dist: isort>=5.12.0; extra == "dev"
Requires-Dist: mypy>=1.0.0; extra == "dev"
Requires-Dist: flake8>=6.0.0; extra == "dev"
Requires-Dist: types-requests>=2.28.0; extra == "dev"
Dynamic: author
Dynamic: home-page
Dynamic: license-file
Dynamic: requires-python
